<!DOCTYPE article
[
<!ENTITY % entities SYSTEM "../shared/syslog-ng-entities.ent">
  %entities;
  ]
 >
<procedure xml:id="configuring_windows_client_for_rltp" xmlns="http://docbook.org/ns/docbook">
    <title>Configuring &agent; clients for RLTP</title>
    <xi:include xmlns:xi="http://www.w3.org/2001/XInclude" href="chunk/step-rltp-windows-client.xml"/>
    <step>
        <para>Remote logging can be tested the same way as described in <xref linkend="installing_client_windows"/>.</para>
    </step>
</procedure>
